filenumutils/__init__.py
filenumutils/filenum_functions.py
filenumutils/helper_functions.py
filenumutils-0.1.2.dist-info/LICENCE
filenumutils-0.1.2.dist-info/METADATA
filenumutils-0.1.2.dist-info/WHEEL
filenumutils-0.1.2.dist-info/top_level.txt
filenumutils-0.1.2.dist-info/RECORD
