Metadata-Version: 2.1
Name: filenumutils
Version: 0.1.2
Summary: Python tools to find last file/folder number in a int indexed file/folder with specified extension, prefix and/or suffix. Also allows to create next folder, e.g if dir contains train_00 and train_01, it creates train_02
Home-page: https://github.com/saravanabalagi/filenumutils
Author: Saravanabalagi Ramachandran
Author-email: saravanabalagi@hotmail.com
License: MIT
Platform: UNKNOWN
Classifier: Development Status :: 4 - Beta
Classifier: Topic :: Software Development :: Libraries
Classifier: License :: OSI Approved :: MIT License
Classifier: Programming Language :: Python :: 3
Classifier: Programming Language :: Python :: 3.6
Classifier: Programming Language :: Python :: 3.7
License-File: LICENCE
